K2600acceslib/__init__.py
K2600acceslib/kth2600.py
K2600acceslib/kth_integration.py
K2600acceslib-0.0.3.dist-info/METADATA
K2600acceslib-0.0.3.dist-info/WHEEL
K2600acceslib-0.0.3.dist-info/top_level.txt
K2600acceslib-0.0.3.dist-info/RECORD
