Metadata-Version: 2.1
Name: K2600acceslib
Version: 0.0.3
Summary: This lib controls using 'pyvisa' a keithley series 2600
Home-page: UNKNOWN
License: CC0 1.0 Universal
Platform: UNKNOWN
Classifier: Development Status :: 4 - Beta
Classifier: Programming Language :: Python :: 3
Requires-Python: >=3
Requires-Dist: PyVISA (==1.11.3)
Requires-Dist: PyVISA-py (==0.5.2)
Requires-Dist: typing-extensions (==4.1.1)
